oodle/__init__.py
oodle/channels.py
oodle/mutex.py
oodle/patches/__init__.py
oodle/patches/patch_time.py
oodle/shields.py
oodle/spawners.py
oodle/thread_groups.py
oodle/threads.py
oodle/utilities.py
oodle-0.1.4.dist-info/LICENSE
oodle-0.1.4.dist-info/METADATA
oodle-0.1.4.dist-info/WHEEL
oodle-0.1.4.dist-info/RECORD
