Metadata-Version: 2.1
Name: oodle
Version: 0.1.4
Summary: Oodle is a package that makes it easier to manage threads.
License: MIT
Author: Zech Zimmerman
Author-email: hi@zech.codes
Requires-Python: >=3.13,<4.0
Classifier: License :: OSI Approved :: MIT License
Classifier: Programming Language :: Python :: 3
Classifier: Programming Language :: Python :: 3.13
